<?xml version="1.0"?>
<ruleset name="TestMonitor PMD ruleset" xmlns="http://pmd.sf.net/ruleset/1.0.0"
         xmlns:xsi="http://www.w3.org/2001/XMLSchema-instance"
         xsi:schemaLocation="http://pmd.sf.net/ruleset/1.0.0 http://pmd.sf.net/ruleset_xml_schema.xsd"
         xsi:noNamespaceSchemaLocation=" http://pmd.sf.net/ruleset_xml_schema.xsd">
    <description>TestMonitor PMD ruleset</description>

    <rule ref="rulesets/cleancode.xml">
        <exclude name="StaticAccess"/>
    </rule>
    <rule ref="rulesets/codesize.xml">
        <exclude name="TooManyMethods"/>
        <exclude name="TooManyPublicMethods"/>
    </rule>
    <rule ref="rulesets/codesize.xml/TooManyMethods">
        <properties>
            <property name="maxmethods" value="25" description="The method count reporting threshold."/>
        </properties>
    </rule>
    <rule ref="rulesets/codesize.xml/TooManyPublicMethods">
        <properties>
            <property name="maxmethods" value="15" description="The method count reporting threshold."/>
        </properties>
    </rule>
    <rule ref="rulesets/controversial.xml"/>
    <rule ref="rulesets/design.xml">
        <exclude name="NumberOfChildren"/>
    </rule>
    <rule ref="rulesets/design.xml/NumberOfChildren">
        <properties>
            <property name="minimum" value="25" description="Maximum number of acceptable child classes."/>
        </properties>
    </rule>
    <rule ref="rulesets/naming.xml">
        <exclude name="LongVariable"/>
        <exclude name="ShortVariable"/>
        <exclude name="BooleanGetMethodName"/>
    </rule>
    <rule ref="rulesets/unusedcode.xml">
    </rule>
</ruleset>
